{
  "url": "https://www.hk01.com/%E7%AA%81%E7%99%BC/60298678/%E5%AE%8F%E7%A6%8F%E8%8B%91%E5%A4%A7%E7%81%AB-%E7%94%9F%E9%82%84%E8%80%85%E5%89%96%E7%99%BD2-5%E5%B0%8F%E6%99%82%E7%81%AB%E5%8A%AB-%E6%95%91%E4%BA%BA%E7%8D%B2%E8%AE%9A%E8%AC%99%E7%A8%B1-%E6%88%91%E5%94%94%E4%BF%82%E8%8B%B1%E9%9B%84",
  "title": "宏福苑大火｜生還者剖白2.5小時火劫　救人獲讚謙稱：我唔係英雄",
  "source": "hk01",
  "source_file": "content\\news\\hk01\\README.md",
  "scraped_at": "2025-12-01T17:03:13.827243",
  "archive_path": "content\\news\\hk01\\archive\\宏福苑大火生還者剖白25小時火劫-救人獲讚謙稱我唔係英雄-1"
}