{
  "url": "https://news.tvb.com/tc/taipofire/692d04c2ada134dbdf27096a/%E5%AE%8F%E7%A6%8F%E8%8B%91%E4%BA%94%E7%B4%9A%E7%81%AB-%E5%AE%8F%E7%A6%8F%E8%8B%91%E4%BA%94%E7%B4%9A%E7%81%AB%EF%BD%9C%E8%AD%A6%E6%96%B9%E7%81%BD%E9%9B%A3%E9%81%87%E5%AE%B3%E8%80%85%E8%BE%A8%E8%AA%8D%E7%B5%84%E4%BA%BA%E5%93%A1%E5%86%8D%E5%88%B0%E7%8F%BE%E5%A0%B4-%E5%B1%95%E9%96%8B%E7%AC%AC%E4%B8%89%E6%97%A5%E6%90%9C%E7%B4%A2",
  "title": "宏福苑五級火｜警方災難遇害者辨認組人員再到現場 展開第三日搜索 宏福苑五級火 12小時前 粵",
  "source": "tvb",
  "source_file": "content\\news\\tvb\\README.md",
  "scraped_at": "2025-12-01T17:08:16.469356",
  "archive_path": "content\\news\\tvb\\archive\\宏福苑五級火警方災難遇害者辨認組人員再到現場-展開第三日搜索-宏福苑五級火-12小時前-粵"
}